example/__init__.py
scregat/__init__.py
scregat/data_process.py
scregat/data_process_txm.py
scregat/model.py
scregat/model_txm.py
scregat/data/PO.txt
scregat/data/PP.txt
scregat/data/genes.protein.tss.tsv
scregat/data/hg38.chrom.sizes
scregat/data/trrust_rawdata.human.tsv
scregat/tools/liftOver
scregat/tools/bedtools/bin/annotateBed
scregat/tools/bedtools/bin/bamToBed
scregat/tools/bedtools/bin/bamToFastq
scregat/tools/bedtools/bin/bed12ToBed6
scregat/tools/bedtools/bin/bedToBam
scregat/tools/bedtools/bin/bedToIgv
scregat/tools/bedtools/bin/bedpeToBam
scregat/tools/bedtools/bin/bedtools
scregat/tools/bedtools/bin/closestBed
scregat/tools/bedtools/bin/clusterBed
scregat/tools/bedtools/bin/complementBed
scregat/tools/bedtools/bin/coverageBed
scregat/tools/bedtools/bin/expandCols
scregat/tools/bedtools/bin/fastaFromBed
scregat/tools/bedtools/bin/flankBed
scregat/tools/bedtools/bin/genomeCoverageBed
scregat/tools/bedtools/bin/getOverlap
scregat/tools/bedtools/bin/groupBy
scregat/tools/bedtools/bin/intersectBed
scregat/tools/bedtools/bin/linksBed
scregat/tools/bedtools/bin/mapBed
scregat/tools/bedtools/bin/maskFastaFromBed
scregat/tools/bedtools/bin/mergeBed
scregat/tools/bedtools/bin/multiBamCov
scregat/tools/bedtools/bin/multiIntersectBed
scregat/tools/bedtools/bin/nucBed
scregat/tools/bedtools/bin/pairToBed
scregat/tools/bedtools/bin/pairToPair
scregat/tools/bedtools/bin/randomBed
scregat/tools/bedtools/bin/shiftBed
scregat/tools/bedtools/bin/shuffleBed
scregat/tools/bedtools/bin/slopBed
scregat/tools/bedtools/bin/sortBed
scregat/tools/bedtools/bin/subtractBed
scregat/tools/bedtools/bin/tagBam
scregat/tools/bedtools/bin/unionBedGraphs
scregat/tools/bedtools/bin/windowBed
scregat/tools/bedtools/bin/windowMaker
scregat/tools/files_liftOver/hg18ToHg19.over.chain.gz
scregat/tools/files_liftOver/hg19ToHg38.over.chain.gz
scregat/tools/files_liftOver/hg38ToHg19.over.chain.gz
scReGAT-0.0.13.dist-info/LICENSE
scReGAT-0.0.13.dist-info/METADATA
scReGAT-0.0.13.dist-info/WHEEL
scReGAT-0.0.13.dist-info/top_level.txt
scReGAT-0.0.13.dist-info/RECORD
