Metadata-Version: 2.1
Name: scReGAT
Version: 0.0.13
Summary: A GAT-based computational framework to predict long-range gene regulatory relationships
Home-page: https://github.com/Drizzle-Zhang/scReGAT
Author: Yu Zhang
Author-email: zhang_yu18@fudan.edu.cn
License: MIT
Classifier: License :: OSI Approved :: MIT License
Classifier: Programming Language :: Python :: 3
Classifier: Programming Language :: Python :: 3.8
Classifier: Programming Language :: Python :: 3.9
Classifier: Programming Language :: Python :: 3.10
Classifier: Programming Language :: Python :: Implementation :: CPython
Classifier: Programming Language :: Python :: Implementation :: PyPy
Requires-Python: >=3.8.3
License-File: LICENSE
Requires-Dist: numpy
Requires-Dist: pandas
Requires-Dist: scikit-learn
Requires-Dist: scipy
Requires-Dist: statsmodels
Requires-Dist: anndata
Requires-Dist: scanpy
Requires-Dist: episcanpy (==0.3.1)
Requires-Dist: cosg
Requires-Dist: torch
Requires-Dist: pyg-lib
Requires-Dist: torch-scatter
Requires-Dist: torch-sparse
Requires-Dist: torch-cluster
Requires-Dist: torch-spline-conv
Requires-Dist: torch-geometric
Requires-Dist: captum
Requires-Dist: audtorch
